<?xml version="1.0" encoding="UTF-8" standalone="yes"?>

</item>
<title>[COLOR white]Los Simpson[/COLOR] [COLOR green]Temporada 02 capitulo 01[/COLOR]</title>       
<urlsolve>http://gamovideo.com/lmfsboi5wja2</urlsolve>
<thumbnail>https://raw.githubusercontent.com/RaspberryPiLibreelec/Addon/master/series/lossimpson.png</thumbnail>
<fanart>https://raw.githubusercontent.com/RaspberryPiLibreelec/Addon/master/addon.jpg</fanart>
<info>[COLOR white]Narra la historia de una peculiar familia (Homer, Marge, Bart, Maggie y Lisa Simpson) y otros divertidos personajes de la localidad norteamericana de Springfield. Homer, el padre, es un desastroso inspector de seguridad de una central nuclear. Marge, la madre, es un ama de casa acostumbrada a soportar a su peculiar familia. Bart, de 10 años, intenta divertirse con travesuras de todo tipo. Lisa es la más inteligente de la familia, y Maggie, la más pequeña, es un bebé que todavía no habla, pero que juega un importante papel.[/COLOR]</info>
</item>

<item>
<title>[COLOR white]Los Simpson[/COLOR] [COLOR green]Temporada 02 capitulo 02[/COLOR]</title>       
<urlsolve>http://gamovideo.com/k3xgk8kuwcl7</urlsolve>
<thumbnail>https://raw.githubusercontent.com/RaspberryPiLibreelec/Addon/master/series/lossimpson.png</thumbnail>
<fanart>https://raw.githubusercontent.com/RaspberryPiLibreelec/Addon/master/addon.jpg</fanart>
<info>[COLOR white]Narra la historia de una peculiar familia (Homer, Marge, Bart, Maggie y Lisa Simpson) y otros divertidos personajes de la localidad norteamericana de Springfield. Homer, el padre, es un desastroso inspector de seguridad de una central nuclear. Marge, la madre, es un ama de casa acostumbrada a soportar a su peculiar familia. Bart, de 10 años, intenta divertirse con travesuras de todo tipo. Lisa es la más inteligente de la familia, y Maggie, la más pequeña, es un bebé que todavía no habla, pero que juega un importante papel.[/COLOR]</info>
</item>

<item>
<title>[COLOR white]Los Simpson[/COLOR] [COLOR green]Temporada 02 capitulo 03[/COLOR]</title>       
<urlsolve>http://gamovideo.com/z25c3jbocjus</urlsolve>
<thumbnail>https://raw.githubusercontent.com/RaspberryPiLibreelec/Addon/master/series/lossimpson.png</thumbnail>
<fanart>https://raw.githubusercontent.com/RaspberryPiLibreelec/Addon/master/addon.jpg</fanart>
<info>[COLOR white]Narra la historia de una peculiar familia (Homer, Marge, Bart, Maggie y Lisa Simpson) y otros divertidos personajes de la localidad norteamericana de Springfield. Homer, el padre, es un desastroso inspector de seguridad de una central nuclear. Marge, la madre, es un ama de casa acostumbrada a soportar a su peculiar familia. Bart, de 10 años, intenta divertirse con travesuras de todo tipo. Lisa es la más inteligente de la familia, y Maggie, la más pequeña, es un bebé que todavía no habla, pero que juega un importante papel.[/COLOR]</info>
</item>

<item>
<title>[COLOR white]Los Simpson[/COLOR] [COLOR green]Temporada 02 capitulo 04[/COLOR]</title>       
<urlsolve>http://gamovideo.com/wlil7xi5ujxy</urlsolve>
<thumbnail>https://raw.githubusercontent.com/RaspberryPiLibreelec/Addon/master/series/lossimpson.png</thumbnail>
<fanart>https://raw.githubusercontent.com/RaspberryPiLibreelec/Addon/master/addon.jpg</fanart>
<info>[COLOR white]Narra la historia de una peculiar familia (Homer, Marge, Bart, Maggie y Lisa Simpson) y otros divertidos personajes de la localidad norteamericana de Springfield. Homer, el padre, es un desastroso inspector de seguridad de una central nuclear. Marge, la madre, es un ama de casa acostumbrada a soportar a su peculiar familia. Bart, de 10 años, intenta divertirse con travesuras de todo tipo. Lisa es la más inteligente de la familia, y Maggie, la más pequeña, es un bebé que todavía no habla, pero que juega un importante papel.[/COLOR]</info>
</item>

<item>
<title>[COLOR white]Los Simpson[/COLOR] [COLOR green]Temporada 02 capitulo 05[/COLOR]</title>       
<urlsolve>http://gamovideo.com/mylo79jmwi2l</urlsolve>
<thumbnail>https://raw.githubusercontent.com/RaspberryPiLibreelec/Addon/master/series/lossimpson.png</thumbnail>
<fanart>https://raw.githubusercontent.com/RaspberryPiLibreelec/Addon/master/addon.jpg</fanart>
<info>[COLOR white]Narra la historia de una peculiar familia (Homer, Marge, Bart, Maggie y Lisa Simpson) y otros divertidos personajes de la localidad norteamericana de Springfield. Homer, el padre, es un desastroso inspector de seguridad de una central nuclear. Marge, la madre, es un ama de casa acostumbrada a soportar a su peculiar familia. Bart, de 10 años, intenta divertirse con travesuras de todo tipo. Lisa es la más inteligente de la familia, y Maggie, la más pequeña, es un bebé que todavía no habla, pero que juega un importante papel.[/COLOR]</info>
</item>

<item>
<title>[COLOR white]Los Simpson[/COLOR] [COLOR green]Temporada 02 capitulo 06[/COLOR]</title>       
<urlsolve>http://gamovideo.com/e3omr8b0z2tz</urlsolve>
<thumbnail>https://raw.githubusercontent.com/RaspberryPiLibreelec/Addon/master/series/lossimpson.png</thumbnail>
<fanart>https://raw.githubusercontent.com/RaspberryPiLibreelec/Addon/master/addon.jpg</fanart>
<info>[COLOR white]Narra la historia de una peculiar familia (Homer, Marge, Bart, Maggie y Lisa Simpson) y otros divertidos personajes de la localidad norteamericana de Springfield. Homer, el padre, es un desastroso inspector de seguridad de una central nuclear. Marge, la madre, es un ama de casa acostumbrada a soportar a su peculiar familia. Bart, de 10 años, intenta divertirse con travesuras de todo tipo. Lisa es la más inteligente de la familia, y Maggie, la más pequeña, es un bebé que todavía no habla, pero que juega un importante papel.[/COLOR]</info>
</item>

<item>
<title>[COLOR white]Los Simpson[/COLOR] [COLOR green]Temporada 02 capitulo 07[/COLOR]</title>       
<urlsolve>http://gamovideo.com/9a5mf79rl7qa</urlsolve>
<thumbnail>https://raw.githubusercontent.com/RaspberryPiLibreelec/Addon/master/series/lossimpson.png</thumbnail>
<fanart>https://raw.githubusercontent.com/RaspberryPiLibreelec/Addon/master/addon.jpg</fanart>
<info>[COLOR white]Narra la historia de una peculiar familia (Homer, Marge, Bart, Maggie y Lisa Simpson) y otros divertidos personajes de la localidad norteamericana de Springfield. Homer, el padre, es un desastroso inspector de seguridad de una central nuclear. Marge, la madre, es un ama de casa acostumbrada a soportar a su peculiar familia. Bart, de 10 años, intenta divertirse con travesuras de todo tipo. Lisa es la más inteligente de la familia, y Maggie, la más pequeña, es un bebé que todavía no habla, pero que juega un importante papel.[/COLOR]</info>
</item>

<item>
<title>[COLOR white]Los Simpson[/COLOR] [COLOR green]Temporada 02 capitulo 08[/COLOR]</title>       
<urlsolve>http://gamovideo.com/3z02d6r466ff</urlsolve>
<thumbnail>https://raw.githubusercontent.com/RaspberryPiLibreelec/Addon/master/series/lossimpson.png</thumbnail>
<fanart>https://raw.githubusercontent.com/RaspberryPiLibreelec/Addon/master/addon.jpg</fanart>
<info>[COLOR white]Narra la historia de una peculiar familia (Homer, Marge, Bart, Maggie y Lisa Simpson) y otros divertidos personajes de la localidad norteamericana de Springfield. Homer, el padre, es un desastroso inspector de seguridad de una central nuclear. Marge, la madre, es un ama de casa acostumbrada a soportar a su peculiar familia. Bart, de 10 años, intenta divertirse con travesuras de todo tipo. Lisa es la más inteligente de la familia, y Maggie, la más pequeña, es un bebé que todavía no habla, pero que juega un importante papel.[/COLOR]</info>
</item>

<item>
<title>[COLOR white]Los Simpson[/COLOR] [COLOR green]Temporada 02 capitulo 09[/COLOR]</title>       
<urlsolve>http://gamovideo.com/a4s3f67a8fo1</urlsolve>
<thumbnail>https://raw.githubusercontent.com/RaspberryPiLibreelec/Addon/master/series/lossimpson.png</thumbnail>
<fanart>https://raw.githubusercontent.com/RaspberryPiLibreelec/Addon/master/addon.jpg</fanart>
<info>[COLOR white]Narra la historia de una peculiar familia (Homer, Marge, Bart, Maggie y Lisa Simpson) y otros divertidos personajes de la localidad norteamericana de Springfield. Homer, el padre, es un desastroso inspector de seguridad de una central nuclear. Marge, la madre, es un ama de casa acostumbrada a soportar a su peculiar familia. Bart, de 10 años, intenta divertirse con travesuras de todo tipo. Lisa es la más inteligente de la familia, y Maggie, la más pequeña, es un bebé que todavía no habla, pero que juega un importante papel.[/COLOR]</info>
</item>

<item>
<title>[COLOR white]Los Simpson[/COLOR] [COLOR green]Temporada 02 capitulo 10[/COLOR]</title>       
<urlsolve>http://gamovideo.com/o4kdcdusxhe0</urlsolve>
<thumbnail>https://raw.githubusercontent.com/RaspberryPiLibreelec/Addon/master/series/lossimpson.png</thumbnail>
<fanart>https://raw.githubusercontent.com/RaspberryPiLibreelec/Addon/master/addon.jpg</fanart>
<info>[COLOR white]Narra la historia de una peculiar familia (Homer, Marge, Bart, Maggie y Lisa Simpson) y otros divertidos personajes de la localidad norteamericana de Springfield. Homer, el padre, es un desastroso inspector de seguridad de una central nuclear. Marge, la madre, es un ama de casa acostumbrada a soportar a su peculiar familia. Bart, de 10 años, intenta divertirse con travesuras de todo tipo. Lisa es la más inteligente de la familia, y Maggie, la más pequeña, es un bebé que todavía no habla, pero que juega un importante papel.[/COLOR]</info>
</item>

<item>
<title>[COLOR white]Los Simpson[/COLOR] [COLOR green]Temporada 02 capitulo 11[/COLOR]</title>       
<urlsolve>http://gamovideo.com/vj272s8ndc1f</urlsolve>
<thumbnail>https://raw.githubusercontent.com/RaspberryPiLibreelec/Addon/master/series/lossimpson.png</thumbnail>
<fanart>https://raw.githubusercontent.com/RaspberryPiLibreelec/Addon/master/addon.jpg</fanart>
<info>[COLOR white]Narra la historia de una peculiar familia (Homer, Marge, Bart, Maggie y Lisa Simpson) y otros divertidos personajes de la localidad norteamericana de Springfield. Homer, el padre, es un desastroso inspector de seguridad de una central nuclear. Marge, la madre, es un ama de casa acostumbrada a soportar a su peculiar familia. Bart, de 10 años, intenta divertirse con travesuras de todo tipo. Lisa es la más inteligente de la familia, y Maggie, la más pequeña, es un bebé que todavía no habla, pero que juega un importante papel.[/COLOR]</info>
</item>

<item>
<title>[COLOR white]Los Simpson[/COLOR] [COLOR green]Temporada 02 capitulo 12[/COLOR]</title>       
<urlsolve>http://gamovideo.com/mdkgmua0r1i5</urlsolve>
<thumbnail>https://raw.githubusercontent.com/RaspberryPiLibreelec/Addon/master/series/lossimpson.png</thumbnail>
<fanart>https://raw.githubusercontent.com/RaspberryPiLibreelec/Addon/master/addon.jpg</fanart>
<info>[COLOR white]Narra la historia de una peculiar familia (Homer, Marge, Bart, Maggie y Lisa Simpson) y otros divertidos personajes de la localidad norteamericana de Springfield. Homer, el padre, es un desastroso inspector de seguridad de una central nuclear. Marge, la madre, es un ama de casa acostumbrada a soportar a su peculiar familia. Bart, de 10 años, intenta divertirse con travesuras de todo tipo. Lisa es la más inteligente de la familia, y Maggie, la más pequeña, es un bebé que todavía no habla, pero que juega un importante papel.[/COLOR]</info>
</item>

<item>
<title>[COLOR white]Los Simpson[/COLOR] [COLOR green]Temporada 02 capitulo 13[/COLOR]</title>       
<urlsolve>http://gamovideo.com/barappjmwfwy</urlsolve>
<thumbnail>https://raw.githubusercontent.com/RaspberryPiLibreelec/Addon/master/series/lossimpson.png</thumbnail>
<fanart>https://raw.githubusercontent.com/RaspberryPiLibreelec/Addon/master/addon.jpg</fanart>
<info>[COLOR white]Narra la historia de una peculiar familia (Homer, Marge, Bart, Maggie y Lisa Simpson) y otros divertidos personajes de la localidad norteamericana de Springfield. Homer, el padre, es un desastroso inspector de seguridad de una central nuclear. Marge, la madre, es un ama de casa acostumbrada a soportar a su peculiar familia. Bart, de 10 años, intenta divertirse con travesuras de todo tipo. Lisa es la más inteligente de la familia, y Maggie, la más pequeña, es un bebé que todavía no habla, pero que juega un importante papel.[/COLOR]</info>
</item>

<item>
<title>[COLOR white]Los Simpson[/COLOR] [COLOR green]Temporada 02 capitulo 14[/COLOR]</title>       
<urlsolve>http://gamovideo.com/mcw919f3mszh</urlsolve>
<thumbnail>https://raw.githubusercontent.com/RaspberryPiLibreelec/Addon/master/series/lossimpson.png</thumbnail>
<fanart>https://raw.githubusercontent.com/RaspberryPiLibreelec/Addon/master/addon.jpg</fanart>
<info>[COLOR white]Narra la historia de una peculiar familia (Homer, Marge, Bart, Maggie y Lisa Simpson) y otros divertidos personajes de la localidad norteamericana de Springfield. Homer, el padre, es un desastroso inspector de seguridad de una central nuclear. Marge, la madre, es un ama de casa acostumbrada a soportar a su peculiar familia. Bart, de 10 años, intenta divertirse con travesuras de todo tipo. Lisa es la más inteligente de la familia, y Maggie, la más pequeña, es un bebé que todavía no habla, pero que juega un importante papel.[/COLOR]</info>
</item>

<item>
<title>[COLOR white]Los Simpson[/COLOR] [COLOR green]Temporada 02 capitulo 15[/COLOR]</title>       
<urlsolve>http://gamovideo.com/li1jyk811zy5</urlsolve>
<thumbnail>https://raw.githubusercontent.com/RaspberryPiLibreelec/Addon/master/series/lossimpson.png</thumbnail>
<fanart>https://raw.githubusercontent.com/RaspberryPiLibreelec/Addon/master/addon.jpg</fanart>
<info>[COLOR white]Narra la historia de una peculiar familia (Homer, Marge, Bart, Maggie y Lisa Simpson) y otros divertidos personajes de la localidad norteamericana de Springfield. Homer, el padre, es un desastroso inspector de seguridad de una central nuclear. Marge, la madre, es un ama de casa acostumbrada a soportar a su peculiar familia. Bart, de 10 años, intenta divertirse con travesuras de todo tipo. Lisa es la más inteligente de la familia, y Maggie, la más pequeña, es un bebé que todavía no habla, pero que juega un importante papel.[/COLOR]</info>
</item>

<item>
<title>[COLOR white]Los Simpson[/COLOR] [COLOR green]Temporada 02 capitulo 16[/COLOR]</title>       
<urlsolve>http://gamovideo.com/nyfj05mggwvd</urlsolve>
<thumbnail>https://raw.githubusercontent.com/RaspberryPiLibreelec/Addon/master/series/lossimpson.png</thumbnail>
<fanart>https://raw.githubusercontent.com/RaspberryPiLibreelec/Addon/master/addon.jpg</fanart>
<info>[COLOR white]Narra la historia de una peculiar familia (Homer, Marge, Bart, Maggie y Lisa Simpson) y otros divertidos personajes de la localidad norteamericana de Springfield. Homer, el padre, es un desastroso inspector de seguridad de una central nuclear. Marge, la madre, es un ama de casa acostumbrada a soportar a su peculiar familia. Bart, de 10 años, intenta divertirse con travesuras de todo tipo. Lisa es la más inteligente de la familia, y Maggie, la más pequeña, es un bebé que todavía no habla, pero que juega un importante papel.[/COLOR]</info>
</item>

<item>
<title>[COLOR white]Los Simpson[/COLOR] [COLOR green]Temporada 02 capitulo 17[/COLOR]</title>       
<urlsolve>http://gamovideo.com/h0kg9glynkhw</urlsolve>
<thumbnail>https://raw.githubusercontent.com/RaspberryPiLibreelec/Addon/master/series/lossimpson.png</thumbnail>
<fanart>https://raw.githubusercontent.com/RaspberryPiLibreelec/Addon/master/addon.jpg</fanart>
<info>[COLOR white]Narra la historia de una peculiar familia (Homer, Marge, Bart, Maggie y Lisa Simpson) y otros divertidos personajes de la localidad norteamericana de Springfield. Homer, el padre, es un desastroso inspector de seguridad de una central nuclear. Marge, la madre, es un ama de casa acostumbrada a soportar a su peculiar familia. Bart, de 10 años, intenta divertirse con travesuras de todo tipo. Lisa es la más inteligente de la familia, y Maggie, la más pequeña, es un bebé que todavía no habla, pero que juega un importante papel.[/COLOR]</info>
</item>

<item>
<title>[COLOR white]Los Simpson[/COLOR] [COLOR green]Temporada 02 capitulo 18[/COLOR]</title>       
<urlsolve>http://gamovideo.com/yvr2w5himbth</urlsolve>
<thumbnail>https://raw.githubusercontent.com/RaspberryPiLibreelec/Addon/master/series/lossimpson.png</thumbnail>
<fanart>https://raw.githubusercontent.com/RaspberryPiLibreelec/Addon/master/addon.jpg</fanart>
<info>[COLOR white]Narra la historia de una peculiar familia (Homer, Marge, Bart, Maggie y Lisa Simpson) y otros divertidos personajes de la localidad norteamericana de Springfield. Homer, el padre, es un desastroso inspector de seguridad de una central nuclear. Marge, la madre, es un ama de casa acostumbrada a soportar a su peculiar familia. Bart, de 10 años, intenta divertirse con travesuras de todo tipo. Lisa es la más inteligente de la familia, y Maggie, la más pequeña, es un bebé que todavía no habla, pero que juega un importante papel.[/COLOR]</info>
</item>

<item>
<title>[COLOR white]Los Simpson[/COLOR] [COLOR green]Temporada 02 capitulo 19[/COLOR]</title>       
<urlsolve>http://gamovideo.com/h3e6u4y16ijx</urlsolve>
<thumbnail>https://raw.githubusercontent.com/RaspberryPiLibreelec/Addon/master/series/lossimpson.png</thumbnail>
<fanart>https://raw.githubusercontent.com/RaspberryPiLibreelec/Addon/master/addon.jpg</fanart>
<info>[COLOR white]Narra la historia de una peculiar familia (Homer, Marge, Bart, Maggie y Lisa Simpson) y otros divertidos personajes de la localidad norteamericana de Springfield. Homer, el padre, es un desastroso inspector de seguridad de una central nuclear. Marge, la madre, es un ama de casa acostumbrada a soportar a su peculiar familia. Bart, de 10 años, intenta divertirse con travesuras de todo tipo. Lisa es la más inteligente de la familia, y Maggie, la más pequeña, es un bebé que todavía no habla, pero que juega un importante papel.[/COLOR]</info>
</item>

<item>
<title>[COLOR white]Los Simpson[/COLOR] [COLOR green]Temporada 02 capitulo 20[/COLOR]</title>       
<urlsolve>http://gamovideo.com/qg2x47sxb2zk</urlsolve>
<thumbnail>https://raw.githubusercontent.com/RaspberryPiLibreelec/Addon/master/series/lossimpson.png</thumbnail>
<fanart>https://raw.githubusercontent.com/RaspberryPiLibreelec/Addon/master/addon.jpg</fanart>
<info>[COLOR white]Narra la historia de una peculiar familia (Homer, Marge, Bart, Maggie y Lisa Simpson) y otros divertidos personajes de la localidad norteamericana de Springfield. Homer, el padre, es un desastroso inspector de seguridad de una central nuclear. Marge, la madre, es un ama de casa acostumbrada a soportar a su peculiar familia. Bart, de 10 años, intenta divertirse con travesuras de todo tipo. Lisa es la más inteligente de la familia, y Maggie, la más pequeña, es un bebé que todavía no habla, pero que juega un importante papel.[/COLOR]</info>
</item>

<item>
<title>[COLOR white]Los Simpson[/COLOR] [COLOR green]Temporada 02 capitulo 21[/COLOR]</title>       
<urlsolve>http://gamovideo.com/2vn0fmrgzgwn</urlsolve>
<thumbnail>https://raw.githubusercontent.com/RaspberryPiLibreelec/Addon/master/series/lossimpson.png</thumbnail>
<fanart>https://raw.githubusercontent.com/RaspberryPiLibreelec/Addon/master/addon.jpg</fanart>
<info>[COLOR white]Narra la historia de una peculiar familia (Homer, Marge, Bart, Maggie y Lisa Simpson) y otros divertidos personajes de la localidad norteamericana de Springfield. Homer, el padre, es un desastroso inspector de seguridad de una central nuclear. Marge, la madre, es un ama de casa acostumbrada a soportar a su peculiar familia. Bart, de 10 años, intenta divertirse con travesuras de todo tipo. Lisa es la más inteligente de la familia, y Maggie, la más pequeña, es un bebé que todavía no habla, pero que juega un importante papel.[/COLOR]</info>
</item>

<item>
<title>[COLOR white]Los Simpson[/COLOR] [COLOR green]Temporada 02 capitulo 22[/COLOR]</title>       
<urlsolve></urlsolve>
<thumbnail>https://raw.githubusercontent.com/RaspberryPiLibreelec/Addon/master/series/lossimpson.png</thumbnail>
<fanart>https://raw.githubusercontent.com/RaspberryPiLibreelec/Addon/master/addon.jpg</fanart>
<info>[COLOR white]Narra la historia de una peculiar familia (Homer, Marge, Bart, Maggie y Lisa Simpson) y otros divertidos personajes de la localidad norteamericana de Springfield. Homer, el padre, es un desastroso inspector de seguridad de una central nuclear. Marge, la madre, es un ama de casa acostumbrada a soportar a su peculiar familia. Bart, de 10 años, intenta divertirse con travesuras de todo tipo. Lisa es la más inteligente de la familia, y Maggie, la más pequeña, es un bebé que todavía no habla, pero que juega un importante papel.[/COLOR]</info>
</item>
