<?xml version="1.0" encoding="UTF-8" standalone="yes"?>

<item>
<title>[COLOR white]Juego de tronos Temporada 1[/COLOR]</title>
<link>http://ignoreme</link>
<externallink>https://raw.githubusercontent.com/RaspberryPiLibreelec/Addon/master/series/juegodetronos/juegodetronos1.xml</externallink>
<thumbnail>https://raw.githubusercontent.com/RaspberryPiLibreelec/Addon/master/series/juegodetronos.png</thumbnail>
<fanart>https://raw.githubusercontent.com/RaspberryPiLibreelec/Addon/master/addon.jpg</fanart>
<info>[COLOR white]La historia se desarrolla en un mundo ficticio de carácter medieval donde hay Siete Reinos. Hay tres líneas argumentales principales: la crónica de la guerra civil dinástica por el control de Poniente entre varias familias nobles que aspiran al Trono de Hierro, la creciente amenaza de los Otros, seres desconocidos que viven al otro lado de un inmenso muro de hielo que protege el Norte de Poniente, y el viaje de Daenerys Targaryen, la hija exiliada del rey que fue asesinado en una guerra civil anterior, y que pretende regresar a Poniente para reclamar sus derechos. Tras un largo verano de varios años, el temible invierno se acerca a los Siete Reinos. Lord Eddard 'Ned' Stark, señor de Invernalia, deja sus dominios para ir a la corte de su amigo, el rey Robert Baratheon en Desembarco del Rey, la capital de los Siete Reinos. Stark se convierte en la Mano del Rey e intenta desentrañar una maraña de intrigas que pondrá en peligro su vida y la de todos los suyos. Mientras tanto diversas facciones conspiran con un solo objetivo: apoderarse del trono. [/COLOR]</info>
</item>

<item>
<title>[COLOR white]Juego de tronos Temporada 2[/COLOR]</title>
<link>http://ignoreme</link>
<externallink>https://raw.githubusercontent.com/RaspberryPiLibreelec/Addon/master/series/juegodetronos/juegodetronos2.xml</externallink>
<thumbnail>https://raw.githubusercontent.com/RaspberryPiLibreelec/Addon/master/series/juegodetronos.png</thumbnail>
<fanart>https://raw.githubusercontent.com/RaspberryPiLibreelec/Addon/master/addon.jpg</fanart>
<info>[COLOR white]La historia se desarrolla en un mundo ficticio de carácter medieval donde hay Siete Reinos. Hay tres líneas argumentales principales: la crónica de la guerra civil dinástica por el control de Poniente entre varias familias nobles que aspiran al Trono de Hierro, la creciente amenaza de los Otros, seres desconocidos que viven al otro lado de un inmenso muro de hielo que protege el Norte de Poniente, y el viaje de Daenerys Targaryen, la hija exiliada del rey que fue asesinado en una guerra civil anterior, y que pretende regresar a Poniente para reclamar sus derechos. Tras un largo verano de varios años, el temible invierno se acerca a los Siete Reinos. Lord Eddard 'Ned' Stark, señor de Invernalia, deja sus dominios para ir a la corte de su amigo, el rey Robert Baratheon en Desembarco del Rey, la capital de los Siete Reinos. Stark se convierte en la Mano del Rey e intenta desentrañar una maraña de intrigas que pondrá en peligro su vida y la de todos los suyos. Mientras tanto diversas facciones conspiran con un solo objetivo: apoderarse del trono. [/COLOR]</info>
</item>

<item>
<title>[COLOR white]Juego de tronos Temporada 3[/COLOR]</title>
<link>http://ignoreme</link>
<externallink>https://raw.githubusercontent.com/RaspberryPiLibreelec/Addon/master/series/juegodetronos/juegodetronos3.xml</externallink>
<thumbnail>https://raw.githubusercontent.com/RaspberryPiLibreelec/Addon/master/series/juegodetronos.png</thumbnail>
<fanart>https://raw.githubusercontent.com/RaspberryPiLibreelec/Addon/master/addon.jpg</fanart>
<info>[COLOR white]La historia se desarrolla en un mundo ficticio de carácter medieval donde hay Siete Reinos. Hay tres líneas argumentales principales: la crónica de la guerra civil dinástica por el control de Poniente entre varias familias nobles que aspiran al Trono de Hierro, la creciente amenaza de los Otros, seres desconocidos que viven al otro lado de un inmenso muro de hielo que protege el Norte de Poniente, y el viaje de Daenerys Targaryen, la hija exiliada del rey que fue asesinado en una guerra civil anterior, y que pretende regresar a Poniente para reclamar sus derechos. Tras un largo verano de varios años, el temible invierno se acerca a los Siete Reinos. Lord Eddard 'Ned' Stark, señor de Invernalia, deja sus dominios para ir a la corte de su amigo, el rey Robert Baratheon en Desembarco del Rey, la capital de los Siete Reinos. Stark se convierte en la Mano del Rey e intenta desentrañar una maraña de intrigas que pondrá en peligro su vida y la de todos los suyos. Mientras tanto diversas facciones conspiran con un solo objetivo: apoderarse del trono. [/COLOR]</info>
</item>

<item>
<title>[COLOR white]Juego de tronos Temporada 4[/COLOR]</title>
<link>http://ignoreme</link>
<externallink>https://raw.githubusercontent.com/RaspberryPiLibreelec/Addon/master/series/juegodetronos/juegodetronos4.xml</externallink>
<thumbnail>https://raw.githubusercontent.com/RaspberryPiLibreelec/Addon/master/series/juegodetronos.png</thumbnail>
<fanart>https://raw.githubusercontent.com/RaspberryPiLibreelec/Addon/master/addon.jpg</fanart>
<info>[COLOR white]La historia se desarrolla en un mundo ficticio de carácter medieval donde hay Siete Reinos. Hay tres líneas argumentales principales: la crónica de la guerra civil dinástica por el control de Poniente entre varias familias nobles que aspiran al Trono de Hierro, la creciente amenaza de los Otros, seres desconocidos que viven al otro lado de un inmenso muro de hielo que protege el Norte de Poniente, y el viaje de Daenerys Targaryen, la hija exiliada del rey que fue asesinado en una guerra civil anterior, y que pretende regresar a Poniente para reclamar sus derechos. Tras un largo verano de varios años, el temible invierno se acerca a los Siete Reinos. Lord Eddard 'Ned' Stark, señor de Invernalia, deja sus dominios para ir a la corte de su amigo, el rey Robert Baratheon en Desembarco del Rey, la capital de los Siete Reinos. Stark se convierte en la Mano del Rey e intenta desentrañar una maraña de intrigas que pondrá en peligro su vida y la de todos los suyos. Mientras tanto diversas facciones conspiran con un solo objetivo: apoderarse del trono. [/COLOR]</info>
</item>

<item>
<title>[COLOR white]Juego de tronos Temporada 5[/COLOR]</title>
<link>http://ignoreme</link>
<externallink>https://raw.githubusercontent.com/RaspberryPiLibreelec/Addon/master/series/juegodetronos/juegodetronos5.xml</externallink>
<thumbnail>https://raw.githubusercontent.com/RaspberryPiLibreelec/Addon/master/series/juegodetronos.png</thumbnail>
<fanart>https://raw.githubusercontent.com/RaspberryPiLibreelec/Addon/master/addon.jpg</fanart>
<info>[COLOR white]La historia se desarrolla en un mundo ficticio de carácter medieval donde hay Siete Reinos. Hay tres líneas argumentales principales: la crónica de la guerra civil dinástica por el control de Poniente entre varias familias nobles que aspiran al Trono de Hierro, la creciente amenaza de los Otros, seres desconocidos que viven al otro lado de un inmenso muro de hielo que protege el Norte de Poniente, y el viaje de Daenerys Targaryen, la hija exiliada del rey que fue asesinado en una guerra civil anterior, y que pretende regresar a Poniente para reclamar sus derechos. Tras un largo verano de varios años, el temible invierno se acerca a los Siete Reinos. Lord Eddard 'Ned' Stark, señor de Invernalia, deja sus dominios para ir a la corte de su amigo, el rey Robert Baratheon en Desembarco del Rey, la capital de los Siete Reinos. Stark se convierte en la Mano del Rey e intenta desentrañar una maraña de intrigas que pondrá en peligro su vida y la de todos los suyos. Mientras tanto diversas facciones conspiran con un solo objetivo: apoderarse del trono. [/COLOR]</info>
</item>

<item>
<title>[COLOR white]Juego de tronos Temporada 6[/COLOR]</title>
<link>http://ignoreme</link>
<externallink>https://raw.githubusercontent.com/RaspberryPiLibreelec/Addon/master/series/juegodetronos/juegodetronos6.xml</externallink>
<thumbnail>https://raw.githubusercontent.com/RaspberryPiLibreelec/Addon/master/series/juegodetronos.png</thumbnail>
<fanart>https://raw.githubusercontent.com/RaspberryPiLibreelec/Addon/master/addon.jpg</fanart>
<info>[COLOR white]La historia se desarrolla en un mundo ficticio de carácter medieval donde hay Siete Reinos. Hay tres líneas argumentales principales: la crónica de la guerra civil dinástica por el control de Poniente entre varias familias nobles que aspiran al Trono de Hierro, la creciente amenaza de los Otros, seres desconocidos que viven al otro lado de un inmenso muro de hielo que protege el Norte de Poniente, y el viaje de Daenerys Targaryen, la hija exiliada del rey que fue asesinado en una guerra civil anterior, y que pretende regresar a Poniente para reclamar sus derechos. Tras un largo verano de varios años, el temible invierno se acerca a los Siete Reinos. Lord Eddard 'Ned' Stark, señor de Invernalia, deja sus dominios para ir a la corte de su amigo, el rey Robert Baratheon en Desembarco del Rey, la capital de los Siete Reinos. Stark se convierte en la Mano del Rey e intenta desentrañar una maraña de intrigas que pondrá en peligro su vida y la de todos los suyos. Mientras tanto diversas facciones conspiran con un solo objetivo: apoderarse del trono. [/COLOR]</info>
</item>

<item>
<title>[COLOR white]Juego de tronos Temporada 7[/COLOR]</title>
<link>http://ignoreme</link>
<externallink>https://raw.githubusercontent.com/RaspberryPiLibreelec/Addon/master/series/juegodetronos/juegodetronos7.xml</externallink>
<thumbnail>https://raw.githubusercontent.com/RaspberryPiLibreelec/Addon/master/series/juegodetronos.png</thumbnail>
<fanart>https://raw.githubusercontent.com/RaspberryPiLibreelec/Addon/master/addon.jpg</fanart>
<info>[COLOR white]La historia se desarrolla en un mundo ficticio de carácter medieval donde hay Siete Reinos. Hay tres líneas argumentales principales: la crónica de la guerra civil dinástica por el control de Poniente entre varias familias nobles que aspiran al Trono de Hierro, la creciente amenaza de los Otros, seres desconocidos que viven al otro lado de un inmenso muro de hielo que protege el Norte de Poniente, y el viaje de Daenerys Targaryen, la hija exiliada del rey que fue asesinado en una guerra civil anterior, y que pretende regresar a Poniente para reclamar sus derechos. Tras un largo verano de varios años, el temible invierno se acerca a los Siete Reinos. Lord Eddard 'Ned' Stark, señor de Invernalia, deja sus dominios para ir a la corte de su amigo, el rey Robert Baratheon en Desembarco del Rey, la capital de los Siete Reinos. Stark se convierte en la Mano del Rey e intenta desentrañar una maraña de intrigas que pondrá en peligro su vida y la de todos los suyos. Mientras tanto diversas facciones conspiran con un solo objetivo: apoderarse del trono. [/COLOR]</info>
</item>